{"subjects": [{"title": {"sl": "Koncepti za modeliranje vizualnih informacij I (ALUO)", "en": "Concepts for Modeling of  Visual Information I"}}, {"title": {"sl": "Interaktivnost in oblikovanje informacij", "en": "Interaction and Information Design"}}, {"title": {"sl": "Diplomski seminar", "en": "Diploma seminar"}}, {"title": {"sl": "Diplomski seminar", "en": "Diploma seminar"}}, {"title": {"sl": "Koncepti za modeliranje vizualnih informacij I (ALUO)", "en": "Concepts for Modeling of  Visual Information I"}}, {"title": {"sl": "Koncepti za modeliranje vizualnih informacij III (ALUO)", "en": "Concepts for Modeling of  Visual Information III"}}]}